spotifyimage/__init__.py
spotifyimage/clienthandler.py
spotifyimage/spotifyimage.py
spotify_image_py-1.0.dist-info/METADATA
spotify_image_py-1.0.dist-info/WHEEL
spotify_image_py-1.0.dist-info/top_level.txt
spotify_image_py-1.0.dist-info/RECORD
