Metadata-Version: 2.1
Name: spotify-image-py
Version: 1.0
Summary: Simple library to get currently playing song from Spotify, optimal for small projects
Home-page: https://github.com/KarlHlmgrn/spotify-image-py
Author: KarlHlmgrn
Author-email: karlhlmgrn.github@gmail.com
Requires-Dist: Flask (>=2.2.2)
Requires-Dist: Pillow (>=9.2.0)
Requires-Dist: qrcode (>=7.3.1)
Requires-Dist: requests (>=2.25.1)
Requires-Dist: six (>=1.16.0)
